<osm version="0.6" generator="openstreetmap-cgimap 2.1.0 (3893119 spike-07.openstreetmap.org)" copyright="OpenStreetMap and contributors" attribution="http://www.openstreetmap.org/copyright" license="http://opendatacommons.org/licenses/odbl/1-0/">
<relation id="9331329" visible="true" version="63" changeset="173937160" timestamp="2025-10-29T16:05:10Z" user="anonymous123123" uid="22067548">
<member type="way" ref="886519754" role=""/>
<member type="way" ref="1085554128" role=""/>
<member type="way" ref="933377818" role=""/>
<member type="way" ref="1085554129" role=""/>
<member type="way" ref="1085554130" role=""/>
<member type="way" ref="933377819" role=""/>
<member type="way" ref="1085554131" role=""/>
<member type="way" ref="846917787" role=""/>
<member type="way" ref="1148836512" role=""/>
<member type="way" ref="880238754" role=""/>
<member type="way" ref="1443944291" role=""/>
<member type="way" ref="1443944292" role=""/>
<member type="way" ref="881243605" role=""/>
<member type="way" ref="881243605" role=""/>
<member type="way" ref="1443944292" role=""/>
<member type="way" ref="1443944291" role=""/>
<member type="way" ref="886723999" role=""/>
<member type="way" ref="420015866" role=""/>
<member type="way" ref="477560866" role=""/>
<member type="way" ref="830097506" role=""/>
<member type="way" ref="680746829" role=""/>
<member type="way" ref="680746832" role=""/>
<member type="way" ref="680746835" role=""/>
<member type="way" ref="477560871" role=""/>
<member type="way" ref="245324555" role=""/>
<member type="way" ref="283872949" role=""/>
<member type="way" ref="700571230" role=""/>
<member type="way" ref="283872951" role=""/>
<member type="way" ref="880729144" role=""/>
<member type="way" ref="252837222" role=""/>
<member type="way" ref="967291241" role=""/>
<member type="way" ref="283873537" role=""/>
<member type="way" ref="283873540" role=""/>
<member type="way" ref="283873542" role=""/>
<member type="way" ref="283872946" role=""/>
<member type="way" ref="700571229" role=""/>
<member type="way" ref="1136910858" role=""/>
<member type="way" ref="1443944308" role=""/>
<member type="way" ref="1443944305" role=""/>
<member type="way" ref="1443944306" role=""/>
<member type="way" ref="1443944307" role=""/>
<member type="way" ref="880729143" role=""/>
<member type="way" ref="255477932" role=""/>
<member type="way" ref="283872537" role=""/>
<member type="way" ref="342056182" role=""/>
<member type="way" ref="679124935" role=""/>
<member type="way" ref="679124936" role=""/>
<member type="way" ref="878258280" role=""/>
<member type="way" ref="1433299573" role=""/>
<member type="way" ref="504359483" role=""/>
<member type="way" ref="680769587" role=""/>
<member type="way" ref="680768256" role=""/>
<member type="way" ref="680769575" role=""/>
<member type="way" ref="880629227" role=""/>
<member type="way" ref="824708853" role=""/>
<member type="way" ref="354316685" role=""/>
<member type="way" ref="1443944289" role=""/>
<member type="way" ref="1443944290" role=""/>
<member type="way" ref="532662029" role=""/>
<member type="way" ref="680769567" role=""/>
<member type="way" ref="680768102" role=""/>
<member type="way" ref="477560872" role=""/>
<member type="way" ref="532566615" role=""/>
<member type="way" ref="680768255" role=""/>
<member type="way" ref="680768254" role=""/>
<member type="way" ref="680768100" role=""/>
<member type="way" ref="680766697" role=""/>
<member type="way" ref="680766696" role=""/>
<member type="way" ref="680765811" role=""/>
<member type="way" ref="680765865" role=""/>
<member type="way" ref="354316684" role=""/>
<member type="way" ref="1443944295" role=""/>
<member type="way" ref="1443944296" role=""/>
<member type="way" ref="253677235" role=""/>
<member type="way" ref="558067366" role=""/>
<member type="way" ref="558067364" role=""/>
<member type="way" ref="253677236" role=""/>
<member type="way" ref="253677237" role=""/>
<member type="way" ref="680768257" role=""/>
<member type="way" ref="680768097" role=""/>
<member type="way" ref="680768098" role=""/>
<member type="way" ref="680766699" role=""/>
<member type="way" ref="680766701" role=""/>
<member type="way" ref="680765810" role=""/>
<member type="way" ref="680765866" role=""/>
<member type="way" ref="523473772" role=""/>
<member type="way" ref="1443944294" role=""/>
<member type="way" ref="1443944293" role=""/>
<member type="way" ref="824708854" role=""/>
<member type="way" ref="680754528" role=""/>
<member type="way" ref="680754530" role=""/>
<member type="way" ref="878972739" role=""/>
<member type="way" ref="878972740" role=""/>
<member type="way" ref="680753528" role=""/>
<member type="way" ref="684438554" role=""/>
<member type="way" ref="680753526" role=""/>
<member type="way" ref="684438558" role=""/>
<member type="way" ref="680749605" role=""/>
<member type="way" ref="684556514" role=""/>
<member type="way" ref="680749600" role=""/>
<member type="way" ref="1443944297" role=""/>
<member type="way" ref="1443944298" role=""/>
<member type="way" ref="1281397103" role=""/>
<member type="way" ref="680793580" role=""/>
<member type="way" ref="1443944303" role=""/>
<member type="way" ref="1443944304" role=""/>
<member type="way" ref="283872536" role=""/>
<member type="way" ref="342056180" role=""/>
<member type="way" ref="245324560" role=""/>
<member type="way" ref="255039977" role=""/>
<member type="way" ref="878258281" role=""/>
<member type="way" ref="255039976" role=""/>
<member type="way" ref="680754531" role=""/>
<member type="way" ref="680754527" role=""/>
<member type="way" ref="878972737" role=""/>
<member type="way" ref="878972738" role=""/>
<member type="way" ref="680791433" role=""/>
<member type="way" ref="680753525" role=""/>
<member type="way" ref="684438553" role=""/>
<member type="way" ref="684438555" role=""/>
<member type="way" ref="680749610" role=""/>
<member type="way" ref="680749595" role=""/>
<member type="way" ref="1443944300" role=""/>
<member type="way" ref="1443944299" role=""/>
<member type="way" ref="523473773" role=""/>
<member type="way" ref="1443944302" role=""/>
<member type="way" ref="1443944301" role=""/>
<member type="way" ref="507856227" role=""/>
<member type="way" ref="283872950" role=""/>
<member type="way" ref="283872943" role=""/>
<member type="way" ref="245324558" role=""/>
<member type="way" ref="245324557" role=""/>
<tag k="addr:city" v="Sebeș"/>
<tag k="distance" v="17"/>
<tag k="name" v="A10 - Lot 1 (Sebes-Alba Iulia)"/>
<tag k="network" v="RO:A"/>
<tag k="route" v="road"/>
<tag k="type" v="route"/>
</relation>
</osm>